unicorn_binance_trailing_stop_loss/__init__.pypy38-pp73-win_amd64.pyd
unicorn_binance_trailing_stop_loss/cli.pypy38-pp73-win_amd64.pyd
unicorn_binance_trailing_stop_loss/manager.pypy38-pp73-win_amd64.pyd
unicorn_binance_trailing_stop_loss-1.1.0.dist-info/LICENSE
unicorn_binance_trailing_stop_loss-1.1.0.dist-info/METADATA
unicorn_binance_trailing_stop_loss-1.1.0.dist-info/WHEEL
unicorn_binance_trailing_stop_loss-1.1.0.dist-info/entry_points.txt
unicorn_binance_trailing_stop_loss-1.1.0.dist-info/top_level.txt
unicorn_binance_trailing_stop_loss-1.1.0.dist-info/RECORD
