Metadata-Version: 2.1
Name: unicorn-binance-trailing-stop-loss
Version: 1.1.0
Summary: A Python library with a command line interface for a trailing stop loss and smart entry on the Binance exchange.
Home-page: https://github.com/LUCIT-Systems-and-Development/unicorn-binance-trailing-stop-loss
Author: LUCIT Systems and Development
Author-email: info@lucit.tech
License: LSOSL - LUCIT Synergetic Open Source License
Project-URL: Documentation, https://lucit-systems-and-development.github.io/unicorn-binance-trailing-stop-loss
Project-URL: Wiki, https://github.com/LUCIT-Systems-and-Development/unicorn-binance-trailing-stop-loss/wiki
Project-URL: Author, https://www.lucit.tech
Project-URL: Changes, https://unicorn-binance-trailing-stop-loss.docs.lucit.tech/changelog.html
Project-URL: License, https://unicorn-binance-trailing-stop-loss.docs.lucit.tech/license.html
Project-URL: Issue Tracker, https://github.com/LUCIT-Systems-and-Development/unicorn-binance-trailing-stop-loss/issues
Project-URL: Chat, https://gitter.im/unicorn-binance-suite/unicorn-binance-trailing-stop-loss
Project-URL: Telegram, https://t.me/unicorndevs
Project-URL: Get Support, https://www.lucit.tech/get-support.html
Project-URL: LUCIT Online Shop, https://shop.lucit.services/software
Keywords: Binance,Binance Futures,Binance Margin,Binance Isolated Margin,Binance Testnet,Trailing Stop Loss,Smart Entry
Classifier: Development Status :: 5 - Production/Stable
Classifier: Programming Language :: Python :: 3.7
Classifier: Programming Language :: Python :: 3.8
Classifier: Programming Language :: Python :: 3.9
Classifier: Programming Language :: Python :: 3.10
Classifier: Programming Language :: Python :: 3.11
Classifier: Programming Language :: Python :: 3.12
Classifier: License :: Other/Proprietary License
Classifier: Intended Audience :: Developers
Classifier: Intended Audience :: Financial and Insurance Industry
Classifier: Intended Audience :: Information Technology
Classifier: Intended Audience :: Science/Research
Classifier: Operating System :: OS Independent
Classifier: Topic :: Office/Business :: Financial :: Investment
Classifier: Topic :: Software Development :: Libraries :: Python Modules
Requires-Python: >=3.7.0
License-File: LICENSE
Requires-Dist: lucit-licensing-python >=1.8.1
Requires-Dist: Cython
Requires-Dist: requests
Requires-Dist: unicorn-binance-websocket-api >=2.1.1
Requires-Dist: unicorn-binance-rest-api >=2.2.0
